{"versions":[{"itemname":"MB0201A06","projectname":"1","first":1,"second":0,"third":0,"message":"初建工程"},{"itemname":"MB0201A06","projectname":"1","first":1,"second":0,"third":1,"message":"工程调试"},{"itemname":"MB0201A06","projectname":"1","first":1,"second":0,"third":2,"message":"优化电机参数"},{"itemname":"MB0201A06","projectname":"1","first":1,"second":0,"third":3,"message":"工程调试"},{"itemname":"MB0201A06","projectname":"1","first":1,"second":0,"third":4,"message":"工程调试"},{"itemname":"MB0201A06","projectname":"1","first":1,"second":0,"third":5,"message":"修复旋转阀配置问题"}]}